{"sha":"a90caf7b7b3e70fb61b57c6dce6710d78debbfcd","node_id":"MDY6Q29tbWl0NTI5ODc5MDphOTBjYWY3YjdiM2U3MGZiNjFiNTdjNmRjZTY3MTBkNzhkZWJiZmNk","commit":{"author":{"name":"Randy Mackay","email":"rmackay9@yahoo.com","date":"2015-05-18T11:51:14Z"},"committer":{"name":"Randy Mackay","email":"rmackay9@yahoo.com","date":"2015-05-19T04:25:42Z"},"message":"l3gd20: faster gyro interrupts","tree":{"sha":"92cbdcb24a170a34e3cdc63c882a5b230177c8ab","url":"https://api.github.com/repos/PX4/PX4-Autopilot/git/trees/92cbdcb24a170a34e3cdc63c882a5b230177c8ab"},"url":"https://api.github.com/repos/PX4/PX4-Autopilot/git/commits/a90caf7b7b3e70fb61b57c6dce6710d78debbfcd","comment_count":0,"verification":{"verified":false,"reason":"unsigned","signature":null,"payload":null}},"url":"https://api.github.com/repos/PX4/PX4-Autopilot/commits/a90caf7b7b3e70fb61b57c6dce6710d78debbfcd","html_url":"https://github.com/PX4/PX4-Autopilot/commit/a90caf7b7b3e70fb61b57c6dce6710d78debbfcd","comments_url":"https://api.github.com/repos/PX4/PX4-Autopilot/commits/a90caf7b7b3e70fb61b57c6dce6710d78debbfcd/comments","author":{"login":"rmackay9","id":1498098,"node_id":"MDQ6VXNlcjE0OTgwOTg=","avatar_url":"https://avatars.githubusercontent.com/u/1498098?v=4","gravatar_id":"","url":"https://api.github.com/users/rmackay9","html_url":"https://github.com/rmackay9","followers_url":"https://api.github.com/users/rmackay9/followers","following_url":"https://api.github.com/users/rmackay9/following{/other_user}","gists_url":"https://api.github.com/users/rmackay9/gists{/gist_id}","starred_url":"https://api.github.com/users/rmackay9/starred{/owner}{/repo}","subscriptions_url":"https://api.github.com/users/rmackay9/subscriptions","organizations_url":"https://api.github.com/users/rmackay9/orgs","repos_url":"https://api.github.com/users/rmackay9/repos","events_url":"https://api.github.com/users/rmackay9/events{/privacy}","received_events_url":"https://api.github.com/users/rmackay9/received_events","type":"User","site_admin":false},"committer":{"login":"rmackay9","id":1498098,"node_id":"MDQ6VXNlcjE0OTgwOTg=","avatar_url":"https://avatars.githubusercontent.com/u/1498098?v=4","gravatar_id":"","url":"https://api.github.com/users/rmackay9","html_url":"https://github.com/rmackay9","followers_url":"https://api.github.com/users/rmackay9/followers","following_url":"https://api.github.com/users/rmackay9/following{/other_user}","gists_url":"https://api.github.com/users/rmackay9/gists{/gist_id}","starred_url":"https://api.github.com/users/rmackay9/starred{/owner}{/repo}","subscriptions_url":"https://api.github.com/users/rmackay9/subscriptions","organizations_url":"https://api.github.com/users/rmackay9/orgs","repos_url":"https://api.github.com/users/rmackay9/repos","events_url":"https://api.github.com/users/rmackay9/events{/privacy}","received_events_url":"https://api.github.com/users/rmackay9/received_events","type":"User","site_admin":false},"parents":[{"sha":"c06ba047e2ded236b8ce5e17694dfca8b8d6f067","url":"https://api.github.com/repos/PX4/PX4-Autopilot/commits/c06ba047e2ded236b8ce5e17694dfca8b8d6f067","html_url":"https://github.com/PX4/PX4-Autopilot/commit/c06ba047e2ded236b8ce5e17694dfca8b8d6f067"}],"stats":{"total":2,"additions":1,"deletions":1},"files":[{"sha":"82c18b5c142c12ebbe7ec05b7fe2c2876f448015","filename":"src/drivers/l3gd20/l3gd20.cpp","status":"modified","additions":1,"deletions":1,"changes":2,"blob_url":"https://github.com/PX4/PX4-Autopilot/blob/a90caf7b7b3e70fb61b57c6dce6710d78debbfcd/src%2Fdrivers%2Fl3gd20%2Fl3gd20.cpp","raw_url":"https://github.com/PX4/PX4-Autopilot/raw/a90caf7b7b3e70fb61b57c6dce6710d78debbfcd/src%2Fdrivers%2Fl3gd20%2Fl3gd20.cpp","contents_url":"https://api.github.com/repos/PX4/PX4-Autopilot/contents/src%2Fdrivers%2Fl3gd20%2Fl3gd20.cpp?ref=a90caf7b7b3e70fb61b57c6dce6710d78debbfcd","patch":"@@ -195,7 +195,7 @@ static const int ERROR = -1;\n   This time reduction is enough to cope with worst case timing jitter\n   due to other timers\n  */\n-#define L3GD20_TIMER_REDUCTION\t\t\t\t200\n+#define L3GD20_TIMER_REDUCTION\t\t\t\t600\n \n extern \"C\" { __EXPORT int l3gd20_main(int argc, char *argv[]); }\n "}]}