{"sha":"d0d9ee373b9eee712a631a1f1e5bb923bdc30e44","node_id":"MDY6Q29tbWl0NTI5ODc5MDpkMGQ5ZWUzNzNiOWVlZTcxMmE2MzFhMWYxZTViYjkyM2JkYzMwZTQ0","commit":{"author":{"name":"Roman","email":"bapstroman@gmail.com","date":"2016-12-15T22:25:17Z"},"committer":{"name":"Lorenz Meier","email":"lorenz@px4.io","date":"2016-12-15T23:15:25Z"},"message":"bebop config: increase logger buffer from 20kB to 200kB\n\nSigned-off-by: Roman <bapstroman@gmail.com>","tree":{"sha":"081620a355654b5f6b71087725285a2c05de4056","url":"https://api.github.com/repos/PX4/PX4-Autopilot/git/trees/081620a355654b5f6b71087725285a2c05de4056"},"url":"https://api.github.com/repos/PX4/PX4-Autopilot/git/commits/d0d9ee373b9eee712a631a1f1e5bb923bdc30e44","comment_count":0,"verification":{"verified":false,"reason":"unsigned","signature":null,"payload":null}},"url":"https://api.github.com/repos/PX4/PX4-Autopilot/commits/d0d9ee373b9eee712a631a1f1e5bb923bdc30e44","html_url":"https://github.com/PX4/PX4-Autopilot/commit/d0d9ee373b9eee712a631a1f1e5bb923bdc30e44","comments_url":"https://api.github.com/repos/PX4/PX4-Autopilot/commits/d0d9ee373b9eee712a631a1f1e5bb923bdc30e44/comments","author":{"login":"RomanBapst","id":7610489,"node_id":"MDQ6VXNlcjc2MTA0ODk=","avatar_url":"https://avatars.githubusercontent.com/u/7610489?v=4","gravatar_id":"","url":"https://api.github.com/users/RomanBapst","html_url":"https://github.com/RomanBapst","followers_url":"https://api.github.com/users/RomanBapst/followers","following_url":"https://api.github.com/users/RomanBapst/following{/other_user}","gists_url":"https://api.github.com/users/RomanBapst/gists{/gist_id}","starred_url":"https://api.github.com/users/RomanBapst/starred{/owner}{/repo}","subscriptions_url":"https://api.github.com/users/RomanBapst/subscriptions","organizations_url":"https://api.github.com/users/RomanBapst/orgs","repos_url":"https://api.github.com/users/RomanBapst/repos","events_url":"https://api.github.com/users/RomanBapst/events{/privacy}","received_events_url":"https://api.github.com/users/RomanBapst/received_events","type":"User","site_admin":false},"committer":{"login":"LorenzMeier","id":1208119,"node_id":"MDQ6VXNlcjEyMDgxMTk=","avatar_url":"https://avatars.githubusercontent.com/u/1208119?v=4","gravatar_id":"","url":"https://api.github.com/users/LorenzMeier","html_url":"https://github.com/LorenzMeier","followers_url":"https://api.github.com/users/LorenzMeier/followers","following_url":"https://api.github.com/users/LorenzMeier/following{/other_user}","gists_url":"https://api.github.com/users/LorenzMeier/gists{/gist_id}","starred_url":"https://api.github.com/users/LorenzMeier/starred{/owner}{/repo}","subscriptions_url":"https://api.github.com/users/LorenzMeier/subscriptions","organizations_url":"https://api.github.com/users/LorenzMeier/orgs","repos_url":"https://api.github.com/users/LorenzMeier/repos","events_url":"https://api.github.com/users/LorenzMeier/events{/privacy}","received_events_url":"https://api.github.com/users/LorenzMeier/received_events","type":"User","site_admin":false},"parents":[{"sha":"5b0a1d4b2a9dce124284fd4d3b4e8a910163f822","url":"https://api.github.com/repos/PX4/PX4-Autopilot/commits/5b0a1d4b2a9dce124284fd4d3b4e8a910163f822","html_url":"https://github.com/PX4/PX4-Autopilot/commit/5b0a1d4b2a9dce124284fd4d3b4e8a910163f822"}],"stats":{"total":2,"additions":1,"deletions":1},"files":[{"sha":"f83071f64895a7433472bb07a31edfc1c3a8182d","filename":"posix-configs/bebop/px4.config","status":"modified","additions":1,"deletions":1,"changes":2,"blob_url":"https://github.com/PX4/PX4-Autopilot/blob/d0d9ee373b9eee712a631a1f1e5bb923bdc30e44/posix-configs%2Fbebop%2Fpx4.config","raw_url":"https://github.com/PX4/PX4-Autopilot/raw/d0d9ee373b9eee712a631a1f1e5bb923bdc30e44/posix-configs%2Fbebop%2Fpx4.config","contents_url":"https://api.github.com/repos/PX4/PX4-Autopilot/contents/posix-configs%2Fbebop%2Fpx4.config?ref=d0d9ee373b9eee712a631a1f1e5bb923bdc30e44","patch":"@@ -40,4 +40,4 @@ mavlink stream -u 14556 -s HIGHRES_IMU -r 50\n mavlink stream -u 14556 -s ATTITUDE -r 50\n df_bebop_bus_wrapper start\n mavlink boot_complete\n-logger start -b 20 -e -t\n+logger start -b 200 -e -t"}]}